coleo/__init__.py
coleo/cli.py
coleo/config.py
coleo/version.py
coleo-0.3.4.dist-info/METADATA
coleo-0.3.4.dist-info/WHEEL
coleo-0.3.4.dist-info/RECORD
