Metadata-Version: 2.3
Name: coleo
Version: 0.3.4
Summary: The nicest way to develop a command-line interface
Project-URL: Homepage, https://github.com/breuleux/coleo
Project-URL: Repository, https://github.com/breuleux/coleo
Author-email: Olivier Breuleux <breuleux@gmail.com>
License-Expression: MIT
Requires-Python: >=3.8
Requires-Dist: ptera~=1.4.1
Provides-Extra: toml
Requires-Dist: toml>=0.10.2; extra == 'toml'
Provides-Extra: yaml
Requires-Dist: pyyaml>=6.0.2; extra == 'yaml'
